{
  "schema_version": "1.0.0",
  "scenario": "moderate",
  "seed": 244,
  "fingerprint": "90b70f786e0ea815",
  "generated_at_utc": "2025-11-18T10:08:43Z",
  "env": {
    "python": "3.10.9",
    "user": "niush"
  },
  "Episode": {
    "Delta": 1.0,
    "T_slots": 3600,
    "seed": 244
  },
  "N_agents": 18,
  "AgentRanges": {
    "lam_sec_min": 0.05,
    "lam_sec_max": 0.2,
    "f_local_min": 800000000.0,
    "f_local_max": 2400000000.0,
    "m_local_min": 3000.0,
    "m_local_max": 8000.0
  },
  "TaskDist": {
    "b_median": 3.0,
    "b_sigma_g": 1.6,
    "rho_median": 1200000000.0,
    "rho_sigma_g": 1.5,
    "mem_median": 64.0,
    "mem_sigma_g": 1.45,
    "p_deadline": 0.25,
    "deadline_min": 0.5,
    "deadline_max": 1.5,
    "p_non_atomic": 0.35,
    "split_ratio_min": 0.3,
    "split_ratio_max": 0.8,
    "modality_probs": null,
    "modality_labels": null
  },
  "units": {
    "Delta": "seconds",
    "lam_sec": "tasks per second (per agent)",
    "per_slot_rate": "lam_sec * Delta",
    "b_mb": "MB",
    "rho_cyc_per_mb": "CPU cycles per MB",
    "c_cycles": "CPU cycles",
    "mem_mb": "MB",
    "deadline_s": "seconds (relative); deadline_time = t_arrival_time + deadline_s",
    "f_local": "Hz",
    "m_local": "MB"
  },
  "notes": {
    "policy_agnostic": true,
    "queueing": "not simulated here",
    "clipping": {
      "enabled": true,
      "method": "lognormal analytic quantile cap",
      "qcap": 0.99,
      "z_table_keys": [
        0.9,
        0.95,
        0.975,
        0.99,
        0.995,
        0.999
      ]
    },
    "action_space_hint": "derived from non_atomic; final decision belongs to environment"
  }
}